nutpie-0.16.3.dist-info/METADATA
nutpie-0.16.3.dist-info/WHEEL
nutpie-0.16.3.dist-info/licenses/LICENSE
nutpie/__init__.py
nutpie/_lib.cpython-312-darwin.so
nutpie/compile_pymc.py
nutpie/compile_stan.py
nutpie/compiled_pyfunc.py
nutpie/normalizing_flow.py
nutpie/sample.py
nutpie/transform_adapter.py
nutpie-0.16.3.dist-info/RECORD
